adcloud/__init__.py
adcloud/builder.py
adcloud/driver.py
adcloud/entities.py
adcloud/errors.py
adcloud/handler.py
adcloud/hive_entities_parser.py
adcloud/phoenix_entities_parser.py
adcloud/settings.py
adcloud_api_py-1.0.4.dev1.dist-info/DESCRIPTION.rst
adcloud_api_py-1.0.4.dev1.dist-info/METADATA
adcloud_api_py-1.0.4.dev1.dist-info/RECORD
adcloud_api_py-1.0.4.dev1.dist-info/WHEEL
adcloud_api_py-1.0.4.dev1.dist-info/metadata.json
adcloud_api_py-1.0.4.dev1.dist-info/top_level.txt
