Metadata-Version: 2.0
Name: adcloud-api-py
Version: 1.0.4.dev1
Summary: Autohome .Corp project
Home-page: https://github.com/calvinjiang/adcloud-api-py
Author: Calvin Jiang
Author-email: jianghuachinacom@163.com
License: MIT
Keywords: adcloud api python
Platform: UNKNOWN
Classifier: Development Status :: 4 - Beta
Classifier: Intended Audience :: Developers
Classifier: Topic :: Software Development :: Build Tools
Classifier: License :: OSI Approved :: MIT License
Classifier: Programming Language :: Python :: 2.6
Classifier: Programming Language :: Python :: 2.7
Classifier: Programming Language :: Python :: 3
Classifier: Programming Language :: Python :: 3.3
Classifier: Programming Language :: Python :: 3.4
Classifier: Programming Language :: Python :: 3.5
Requires-Dist: SQLAlchemy
Requires-Dist: hive-executor-py
Requires-Dist: phoenix-py
Requires-Dist: pipelinedb-py
